[
  {
    "id": 5,
    "user": {"id": 2},
    "ticketType": "MONTH",
    "creationDate": "2024-09-23"
  },
  {
    "id": 6,
    "user": {"id": 2},
    "ticketType": "WEEK",
    "creationDate": "2024-09-23"
  },
  {
    "id": 7,
    "user": {"id": 2},
    "ticketType": "YEAR",
    "creationDate": "2024-09-23"
  },
  {
    "id": 8,
    "user": {"id": 2},
    "ticketType": "DAY",
    "creationDate": "2024-09-23"
  },
  {
    "id": 9,
    "user": {"id": 2},
    "ticketType": "DAY",
    "creationDate": "2024-09-23"
  },
  {
    "id": 10,
    "user": {"id": 2},
    "ticketType": "YEAR",
    "creationDate": "2024-09-23"
  },
  {
    "id": 11,
    "user": {"id": 2},
    "ticketType": "WEEK",
    "creationDate": "2024-09-23"
  },
  {
    "id": 12,
    "user": {"id": 2},
    "ticketType": "MONTH",
    "creationDate": "2024-09-23"
  },
  {
    "id": 13,
    "user": {"id": 3},
    "ticketType": "WEEK",
    "creationDate": "2024-09-23"
  },
  {
    "id": 14,
    "user": {"id": 3},
    "ticketType": "WEEK",
    "creationDate": "2024-09-23"
  },
  {
    "id": 15,
    "user": {"id": 3},
    "ticketType": "WEEK",
    "creationDate": "2024-09-23"
  },
  {
    "id": 16,
    "user": {"id": 3},
    "ticketType": "WEEK",
    "creationDate": "2024-09-23"
  },
  {
    "id": 17,
    "user": {"id": 3},
    "ticketType": "WEEK",
    "creationDate": "2024-09-23"
  },
  {
    "id": 18,
    "user": {"id": 3},
    "ticketType": "WEEK",
    "creationDate": "2024-09-23"
  },
  {
    "id": 19,
    "user": {"id": 3},
    "ticketType": "WEEK",
    "creationDate": "2024-09-23"
  },
  {
    "id": 20,
    "user": {"id": 3},
    "ticketType": "WEEK",
    "creationDate": "2024-09-23"
  },
  {
    "id": 21,
    "user": {"id": 3},
    "ticketType": "WEEK",
    "creationDate": "2024-09-23"
  },
  {
    "id": 22,
    "user": {"id": 3},
    "ticketType": "WEEK",
    "creationDate": "2024-09-23"
  },
  {
    "id": 23,
    "user": {"id": 4},
    "ticketType": "YEAR",
    "creationDate": "2024-09-23"
  },
  {
    "id": 24,
    "user": {"id": 4},
    "ticketType": "WEEK",
    "creationDate": "2024-09-23"
  },
  {
    "id": 25,
    "user": {"id": 4},
    "ticketType": "WEEK",
    "creationDate": "2024-09-23"
  },
  {
    "id": 26,
    "user": {"id": 4},
    "ticketType": "DAY",
    "creationDate": "2024-09-23"
  },
  {
    "id": 27,
    "user": {"id": 4},
    "ticketType": "WEEK",
    "creationDate": "2024-09-23"
  },
  {
    "id": 28,
    "user": {"id": 4},
    "ticketType": "DAY",
    "creationDate": "2024-09-23"
  },
  {
    "id": 30,
    "user": {"id": 5},
    "ticketType": "DAY",
    "creationDate": "2024-09-23"
  },
  {
    "id": 31,
    "user": {"id": 5},
    "ticketType": "DAY",
    "creationDate": "2024-09-23"
  },
  {
    "id": 32,
    "user": {"id": 5},
    "ticketType": "DAY",
    "creationDate": "2024-09-23"
  },
  {
    "id": 33,
    "user": {"id": 5},
    "ticketType": "DAY",
    "creationDate": "2024-09-23"
  },
  {
    "id": 34,
    "user": {"id": 5},
    "ticketType": "DAY",
    "creationDate": "2024-09-23"
  },
  {
    "id": 35,
    "user": {"id": 5},
    "ticketType": "DAY",
    "creationDate": "2024-09-23"
  },
  {
    "id": 36,
    "user": {"id": 5},
    "ticketType": "DAY",
    "creationDate": "2024-09-23"
  },
  {
    "id": 37,
    "user": {"id": 5},
    "ticketType": "DAY",
    "creationDate": "2024-09-23"
  },
  {
    "id": 38,
    "user": {"id": 5},
    "ticketType": "DAY",
    "creationDate": "2024-09-23"
  },
  {
    "id": 39,
    "user": {"id": 5},
    "ticketType": "DAY",
    "creationDate": "2024-09-23"
  },
  {
    "id": 40,
    "user": {"id": 5},
    "ticketType": "DAY",
    "creationDate": "2024-09-23"
  },
  {
    "id": 42,
    "user": {"id": 12},
    "ticketType": "YEAR",
    "creationDate": "2024-09-27"
  },
  {
    "id": 43,
    "user": {"id": 13},
    "ticketType": "DAY",
    "creationDate": "2024-09-27"
  },
  {
    "id": 44,
    "user": {"id": 14},
    "ticketType": "DAY",
    "creationDate": "2024-09-27"
  },
  {
    "id": 45,
    "user": {"id": 4},
    "ticketType": "DAY",
    "creationDate": "2024-10-07"
  },
  {
    "id": 46,
    "user": {"id": 4},
    "ticketType": "DAY",
    "creationDate": "2024-10-07"
  },
  {
    "id": 47,
    "user": {"id": 4},
    "ticketType": "DAY",
    "creationDate": "2024-10-07"
  },
  {
    "id": 51,
    "user": {"id": 6},
    "ticketType": "DAY",
    "creationDate": "2024-10-09"
  },
  {
    "id": 52,
    "user": {"id": 8},
    "ticketType": "DAY",
    "creationDate": "2024-10-09"
  }
]
